ftref/__init__.py
ftref/reflabel.py
ftref_figTree-0.0.3.dist-info/LICENSE
ftref_figTree-0.0.3.dist-info/METADATA
ftref_figTree-0.0.3.dist-info/WHEEL
ftref_figTree-0.0.3.dist-info/top_level.txt
ftref_figTree-0.0.3.dist-info/RECORD
