Metadata-Version: 2.1
Name: ftref-figTree
Version: 0.0.3
Summary: An extension to Kivy's Label widget
Home-page: https://gitlab.com/figTree/reflabel
Author: Jesse Lapere
Author-email: lapere.j@gmail.com
License: UNKNOWN
Platform: UNKNOWN
Classifier: Programming Language :: Python :: 3
Classifier: Intended Audience :: Developers
Classifier: License :: OSI Approved :: GNU General Public License v3 (GPLv3)
Classifier: Topic :: Software Development :: User Interfaces
Classifier: Topic :: Text Processing
Requires-Python: >=3.6
